doozerlib/VERSION
doozerlib/__init__.py
doozerlib/assembly.py
doozerlib/assembly_inspector.py
doozerlib/assertion.py
doozerlib/brew.py
doozerlib/build_status_detector.py
doozerlib/config.py
doozerlib/constants.py
doozerlib/coverity.py
doozerlib/dblib.py
doozerlib/distgit.py
doozerlib/dotconfig.py
doozerlib/exceptions.py
doozerlib/exectools.py
doozerlib/gitdata.py
doozerlib/image.py
doozerlib/logutil.py
doozerlib/metadata.py
doozerlib/model.py
doozerlib/plashet.py
doozerlib/pushd.py
doozerlib/repos.py
doozerlib/rhcos.py
doozerlib/rpm_builder.py
doozerlib/rpmcfg.py
doozerlib/runtime.py
doozerlib/source_modifications.py
doozerlib/state.py
doozerlib/util.py
doozerlib/cli/__init__.py
doozerlib/cli/__main__.py
doozerlib/cli/cli_opts.py
doozerlib/cli/config_plashet.py
doozerlib/cli/detect_embargo.py
doozerlib/cli/get_nightlies.py
doozerlib/cli/images_health.py
doozerlib/cli/images_streams.py
doozerlib/cli/inspect_stream.py
doozerlib/cli/release_calc_upgrade_tests.py
doozerlib/cli/release_gen_assembly.py
doozerlib/cli/release_gen_payload.py
doozerlib/cli/rpms_build.py
doozerlib/cli/scan_sources.py
doozerlib/olm/__init__.py
doozerlib/olm/bundle.py
rh_doozer-2.0.9.dist-info/LICENSE
rh_doozer-2.0.9.dist-info/METADATA
rh_doozer-2.0.9.dist-info/WHEEL
rh_doozer-2.0.9.dist-info/entry_points.txt
rh_doozer-2.0.9.dist-info/top_level.txt
rh_doozer-2.0.9.dist-info/RECORD
