Metadata-Version: 2.1
Name: rh-doozer
Version: 2.0.9
Summary: CLI tool for managing and automating Red Hat software releases
Home-page: https://github.com/openshift/doozer
Author: AOS ART Team
Author-email: aos-team-art@redhat.com
License: Apache License, Version 2.0
Platform: UNKNOWN
Classifier: Development Status :: 5 - Production/Stable
Classifier: Programming Language :: Python :: 3
Classifier: Programming Language :: Python :: 3.6
Classifier: Programming Language :: Python :: 3.7
Classifier: Programming Language :: Python :: 3.8
Classifier: Programming Language :: Python :: 3.9
Classifier: Environment :: Console
Classifier: Operating System :: POSIX
Classifier: License :: OSI Approved :: Apache Software License
Classifier: Intended Audience :: Developers
Classifier: Topic :: Software Development :: Build Tools
Classifier: Natural Language :: English
Requires-Python: >=3.6
Requires-Dist: aiofiles
Requires-Dist: bashlex
Requires-Dist: click (>=6.7)
Requires-Dist: dockerfile-parse (>=0.0.13)
Requires-Dist: future
Requires-Dist: kobo (~=0.19.0)
Requires-Dist: koji
Requires-Dist: PyGitHub (>=1.46)
Requires-Dist: pyyaml (>=5.1)
Requires-Dist: requests
Requires-Dist: requests-kerberos
Requires-Dist: rpm-py-installer
Requires-Dist: semver
Requires-Dist: tenacity
Requires-Dist: wrapt
Requires-Dist: mysql-connector-python (~=8.0.21)
Requires-Dist: python-dateutil (~=2.8.1)
Requires-Dist: openshift-client (~=1.0.12)
Requires-Dist: contextvars ; python_version < "3.7"
